pycity_annek/__init__.py
pycity_annek/cli.py
pycity_annek-0.1.0.dist-info/entry_points.txt
pycity_annek-0.1.0.dist-info/WHEEL
pycity_annek-0.1.0.dist-info/METADATA
pycity_annek-0.1.0.dist-info/RECORD
