Metadata-Version: 2.1
Name: pycity-annek
Version: 0.1.0
Summary: CLI for TeamCity API Requests
License: MIT
Author: Michael MacKenna
Author-email: mmackenna@ufginsurance.com
Requires-Python: >=3.10,<4.0
Classifier: License :: OSI Approved :: MIT License
Classifier: Programming Language :: Python :: 3
Classifier: Programming Language :: Python :: 3.10
Classifier: Programming Language :: Python :: 3.11
Requires-Dist: click (>=8.1.3,<9.0.0)
Requires-Dist: requests (>=2.28.2,<3.0.0)
Requires-Dist: termcolor (>=2.2.0,<3.0.0)
